eventum_core/__init__.py
eventum_core/app.py
eventum_core/batcher.py
eventum_core/plugins_connector.py
eventum_core/py.typed
eventum_core/settings.py
eventum_core/subprocesses.py
eventum_core/tests/test_batcher.py
eventum_core-1.1.4.dist-info/LICENSE
eventum_core-1.1.4.dist-info/METADATA
eventum_core-1.1.4.dist-info/WHEEL
eventum_core-1.1.4.dist-info/RECORD
