Metadata-Version: 2.1
Name: eventum-core
Version: 1.1.4
Summary: Flexible event generator
Home-page: https://github.com/Eventum-Generatives/EventumCore
License: Apache-2.0
Keywords: generator,testing,data,event
Author: Nikita Reznikov
Author-email: nikita.reznikov.public@mail.ru
Requires-Python: >=3.11,<4.0
Classifier: Development Status :: 5 - Production/Stable
Classifier: Intended Audience :: Developers
Classifier: License :: OSI Approved :: Apache Software License
Classifier: Operating System :: OS Independent
Classifier: Programming Language :: Python :: 3
Classifier: Programming Language :: Python :: 3.11
Classifier: Programming Language :: Python :: 3.12
Classifier: Topic :: Software Development :: Testing
Classifier: Topic :: Software Development :: Testing :: Traffic Generation
Requires-Dist: eventum-content-manager (>=1.1.0,<2.0.0)
Requires-Dist: eventum-plugins (>=1.1.0,<2.0.0)
Requires-Dist: jinja2 (>=3.1.3,<4.0.0)
Requires-Dist: pydantic (>=2.6.2,<3.0.0)
Requires-Dist: pytz (>=2024.1,<2025.0)
Requires-Dist: setproctitle (>=1.3.3,<2.0.0)
Project-URL: Documentation, https://eventum-generatives.github.io/Website/
Project-URL: Repository, https://github.com/Eventum-Generatives/EventumCore
